fileer.py
kancyfile.py
fileer-0.0.4.dist-info/METADATA
fileer-0.0.4.dist-info/WHEEL
fileer-0.0.4.dist-info/entry_points.txt
fileer-0.0.4.dist-info/top_level.txt
fileer-0.0.4.dist-info/RECORD
