Metadata-Version: 2.1
Name: fileer
Version: 0.0.4
Summary: 一个文件操作工具类。
Home-page: https://github.com/kancyframework/python-plugins/tree/main/fileer
Author: kancy
Author-email: 793272861@qq.com
License: MIT
Platform: UNKNOWN
Classifier: License :: OSI Approved :: MIT License
Classifier: Programming Language :: Python
Classifier: Programming Language :: Python :: 3
Classifier: Programming Language :: Python :: 3.6
Classifier: Programming Language :: Python :: Implementation :: CPython
Classifier: Programming Language :: Python :: Implementation :: PyPy
Requires-Python: >=3
